django_goncord/__init__.py
django_goncord/apps.py
django_goncord/backends.py
django_goncord/middleware.py
django_goncord-0.2.6.dist-info/LICENSE
django_goncord-0.2.6.dist-info/METADATA
django_goncord-0.2.6.dist-info/WHEEL
django_goncord-0.2.6.dist-info/top_level.txt
django_goncord-0.2.6.dist-info/RECORD
