Metadata-Version: 2.1
Name: django-goncord
Version: 0.2.6
Summary: A django widget which allows you to create multiple auth system.
Home-page: https://github.com/herald-it/django-goncord
Author: herald-it
Author-email: scroll42ru@gmail.com
Maintainer: Dmitry Kuznetsov
Maintainer-email: scroll42ru@gmail.com
License: MIT
Download-URL: https://github.com/herald-it/django-goncord/archive/0.2.6.tar.gz
Keywords: django,auth,goncord,admin
Platform: UNKNOWN
Classifier: Development Status :: 3 - Alpha
Classifier: Framework :: Django
Classifier: Intended Audience :: Developers
Classifier: License :: OSI Approved :: MIT License
Classifier: Natural Language :: Russian
Classifier: Operating System :: OS Independent
Classifier: Programming Language :: Python
Classifier: Programming Language :: Python :: 3
Classifier: Programming Language :: Python :: 3.3
Classifier: Programming Language :: Python :: 3.4
Classifier: Programming Language :: Python :: 3.5
Requires-Dist: setuptools
Requires-Dist: requests
Requires-Dist: Django (<2.0,>=1.11)
